wdt/__init__.py
smwdt-1.0.4.dist-info/LICENSE
smwdt-1.0.4.dist-info/METADATA
smwdt-1.0.4.dist-info/WHEEL
smwdt-1.0.4.dist-info/top_level.txt
smwdt-1.0.4.dist-info/RECORD
